bloggen/.bloggen/.env
bloggen/.bloggen/README.md
bloggen/.bloggen/config.json
bloggen/.bloggen/example.dataSchemas.json
bloggen/.bloggen/example.site.info.json
bloggen/.bloggen/index.html
bloggen/.bloggen/provider.json
bloggen/TODO.md
bloggen/__init__.py
bloggen/__main__.py
bloggen/config.py
bloggen/constants.py
bloggen/generate.py
bloggen/index.html
bloggen/providers.py
bloggen/site_info.py
bloggen/static_site.py
bloggen-0.0.4.dist-info/entry_points.txt
bloggen-0.0.4.dist-info/WHEEL
bloggen-0.0.4.dist-info/METADATA
bloggen-0.0.4.dist-info/RECORD
