Metadata-Version: 2.1
Name: bloggen
Version: 0.0.4
Summary: Deploy a dir of md files as a static site
License: ISC
Author: Lee Harrold
Author-email: halzinnia@gmail.com
Requires-Python: >=3.7,<4.0
Classifier: License :: OSI Approved
Classifier: Programming Language :: Python :: 3
Classifier: Programming Language :: Python :: 3.10
Classifier: Programming Language :: Python :: 3.7
Classifier: Programming Language :: Python :: 3.8
Classifier: Programming Language :: Python :: 3.9
Requires-Dist: Markdown (>=3.4.1,<4.0.0)
Requires-Dist: argparse (>=1.4,<2.0)
Requires-Dist: beautifulsoup4 (>=4.11.1,<5.0.0)
Requires-Dist: google-cloud (>=0.34.0,<0.35.0)
Requires-Dist: google-cloud-storage (>=2.5.0,<3.0.0)
Requires-Dist: pathlib (>=1.0.1,<2.0.0)
